quadriga/__init__.py
quadriga/auth.py
quadriga/private.py
quadriga/public.py
quadrigacx-0.6.1.dist-info/DESCRIPTION.rst
quadrigacx-0.6.1.dist-info/METADATA
quadrigacx-0.6.1.dist-info/RECORD
quadrigacx-0.6.1.dist-info/WHEEL
quadrigacx-0.6.1.dist-info/entry_points.txt
quadrigacx-0.6.1.dist-info/metadata.json
quadrigacx-0.6.1.dist-info/top_level.txt
