Metadata-Version: 2.0
Name: quadrigacx
Version: 0.6.1
Summary: quadrigacx is a Python wrapper for the QuadrigaCX API
Home-page: https://github.com/c4collins/quadrigacx
Author: Connor Collins
Author-email: connor.collins@gmail.com
License: MIT
Keywords: bitcoin quadrigacx web python development
Platform: UNKNOWN
Classifier: Development Status :: 4 - Beta
Classifier: Intended Audience :: Developers
Classifier: Topic :: Software Development
Classifier: License :: OSI Approved :: MIT License
Classifier: Programming Language :: Python :: 2
Classifier: Programming Language :: Python :: 2.7
Requires-Dist: requests
